grailed_api/__init__.py
grailed_api/client/__init__.py
grailed_api/client/client.py
grailed_api/enums/__init__.py
grailed_api/enums/base_category.py
grailed_api/enums/base_entity.py
grailed_api/enums/base_size.py
grailed_api/enums/categories.py
grailed_api/enums/conditions.py
grailed_api/enums/departments.py
grailed_api/enums/labels.py
grailed_api/enums/locations.py
grailed_api/enums/markets.py
grailed_api/enums/sizes.py
grailed_api/exceptions/__init__.py
grailed_api/exceptions/http_error.py
grailed_api/exceptions/wrong_enum_type_error.py
grailed_api/facets/__init__.py
grailed_api/facets/facets.py
grailed_api/models/__init__.py
grailed_api/models/brand.py
grailed_api/models/designer.py
grailed_api/models/highlight_result.py
grailed_api/models/photo.py
grailed_api/models/product.py
grailed_api/models/product_details.py
grailed_api/models/seller_score.py
grailed_api/models/shipping.py
grailed_api/models/user.py
grailed_api/services/__init__.py
grailed_api/services/api_service.py
grailed_api/services/brands_list_service.py
grailed_api/services/products_list_service.py
grailed_api/services/products_retrieve_service.py
grailed_api/session/__init__.py
grailed_api/session/session.py
grailed_api/settings.py
grailed_api-0.1.5.dist-info/LICENSE
grailed_api-0.1.5.dist-info/METADATA
grailed_api-0.1.5.dist-info/WHEEL
grailed_api-0.1.5.dist-info/RECORD
