Metadata-Version: 2.1
Name: grailed_api
Version: 0.1.5
Summary: API exposes most important Grailed API endpoints
Keywords: grailed,api,python,python3
Author: pznamir00
Author-email: pznamir00@gmail.com
Requires-Python: >=3.8,<4.0
Classifier: Programming Language :: Python :: 3
Classifier: Programming Language :: Python :: 3.8
Classifier: Programming Language :: Python :: 3.9
Classifier: Programming Language :: Python :: 3.10
Classifier: Programming Language :: Python :: 3.11
Classifier: Programming Language :: Python :: 3.12
Requires-Dist: aenum (==3.1.15)
Requires-Dist: requests (==2.32.3)
Project-URL: Homepage, https://github.com/pznamir00/Grailed-API
Project-URL: Issues, https://github.com/pznamir00/Grailed-API/issues
